bellman_tools/__init__.py
bellman_tools/dashboard.py
bellman_tools/scheduler_tools.py
bellman_tools/sql_tools.py
bellman_tools/upload_tools.py
bellman_tools/database/Log_Task_Scheduler.py
bellman_tools/database/Task_Scheduled.py
bellman_tools/database/Task_Scheduler.py
bellman_tools/database/Task_Scheduler_Heartbeat.py
bellman_tools/database/__init__.py
bellman_tools/templates/dashboard.html
bellman_tools/templates/login.html
bellman_tools-0.2.1.dist-info/licenses/LICENSE
bellman_tools-0.2.1.dist-info/METADATA
bellman_tools-0.2.1.dist-info/WHEEL
bellman_tools-0.2.1.dist-info/top_level.txt
bellman_tools-0.2.1.dist-info/RECORD
