Metadata-Version: 2.4
Name: bellman_tools
Version: 0.2.1
Summary: A set of tools in Python for data manipulation, database interaction, scheduling and financial analysis for Hedge Funds.
Home-page: https://github.com/davidbellman/bellman_tools
Author: David Bellman
Author-email: david.bellman@bellmancapital.com
License: Proprietary
Classifier: Programming Language :: Python :: 3
Classifier: Programming Language :: Python :: 3.10
Classifier: Programming Language :: Python :: 3.11
Classifier: License :: Other/Proprietary License
Classifier: Operating System :: OS Independent
Classifier: Intended Audience :: Developers
Classifier: Topic :: Database
Requires-Python: >=3.10
License-File: LICENSE
Requires-Dist: pandas
Requires-Dist: numpy
Requires-Dist: sqlalchemy>=2.0
Requires-Dist: pyodbc
Requires-Dist: python-dotenv
Requires-Dist: flask>=2.3.0
Requires-Dist: schedule
Dynamic: author
Dynamic: author-email
Dynamic: classifier
Dynamic: description
Dynamic: description-content-type
Dynamic: home-page
Dynamic: license
Dynamic: license-file
Dynamic: requires-dist
Dynamic: requires-python
Dynamic: summary
